lumes/__main__.py
lumes/core.py
lumes/parse.py
lumes/save.py
lumes-0.0.4a3.dist-info/LICENSE.txt
lumes-0.0.4a3.dist-info/METADATA
lumes-0.0.4a3.dist-info/WHEEL
lumes-0.0.4a3.dist-info/entry_points.txt
lumes-0.0.4a3.dist-info/top_level.txt
lumes-0.0.4a3.dist-info/RECORD
