Metadata-Version: 2.1
Name: lumes
Version: 0.0.4a3
Summary: A simple wraper for screenshot
Home-page: https://github.com/juliancoffee/lumes-py/
License: UNKNOWN
Project-URL: Bug Reports, https://github.com/juliancoffee/lumes-py/issues
Project-URL: Source, https://github.com/juliancoffee/lumes-py/
Keywords: screenshot
Platform: UNKNOWN
Classifier: Development Status :: 3 - Alpha
Classifier: Topic :: Utilities
Classifier: Operating System :: POSIX :: Linux
Classifier: License :: OSI Approved :: MIT License
Classifier: Programming Language :: Python :: 3
Requires-Python: >=3, <4
